{"entries":[{"name":"/api/aggregators","path":"api_http/aggregators","type":"HTTP API"},{"name":"/api/annotation","path":"api_http/annotation/index","type":"HTTP API"},{"name":"/api/annotation/bulk","path":"api_http/annotation/bulk","type":"HTTP API"},{"name":"/api/config","path":"api_http/config/index","type":"HTTP API"},{"name":"/api/config/filters","path":"api_http/config/filters","type":"HTTP API"},{"name":"/api/dropcaches","path":"api_http/dropcaches","type":"HTTP API"},{"name":"/api/put","path":"api_http/put","type":"HTTP API"},{"name":"/api/query","path":"api_http/query/index","type":"HTTP API"},{"name":"/api/query/exp","path":"api_http/query/exp","type":"HTTP API"},{"name":"/api/query/gexp","path":"api_http/query/gexp","type":"HTTP API"},{"name":"/api/query/last","path":"api_http/query/last","type":"HTTP API"},{"name":"/api/rollup","path":"api_http/rollup","type":"HTTP API"},{"name":"/api/search","path":"api_http/search/index","type":"HTTP API"},{"name":"/api/search/lookup","path":"api_http/search/lookup","type":"HTTP API"},{"name":"/api/serializers","path":"api_http/serializers","type":"HTTP API"},{"name":"/api/stats","path":"api_http/stats/index","type":"HTTP API"},{"name":"/api/stats/jvm","path":"api_http/stats/jvm","type":"HTTP API"},{"name":"/api/stats/query","path":"api_http/stats/query","type":"HTTP API"},{"name":"/api/stats/region_clients","path":"api_http/stats/region_clients","type":"HTTP API"},{"name":"/api/stats/threads","path":"api_http/stats/threads","type":"HTTP API"},{"name":"/api/suggest","path":"api_http/suggest","type":"HTTP API"},{"name":"/api/tree","path":"api_http/tree/index","type":"HTTP API"},{"name":"/api/tree/branch","path":"api_http/tree/branch","type":"HTTP API"},{"name":"/api/tree/collisions","path":"api_http/tree/collisions","type":"HTTP API"},{"name":"/api/tree/notmatched","path":"api_http/tree/notmatched","type":"HTTP API"},{"name":"/api/tree/rule","path":"api_http/tree/rule","type":"HTTP API"},{"name":"/api/tree/rules","path":"api_http/tree/rules","type":"HTTP API"},{"name":"/api/tree/test","path":"api_http/tree/test","type":"HTTP API"},{"name":"/api/uid","path":"api_http/uid/index","type":"HTTP API"},{"name":"/api/uid/assign","path":"api_http/uid/assign","type":"HTTP API"},{"name":"/api/uid/tsmeta","path":"api_http/uid/tsmeta","type":"HTTP API"},{"name":"/api/uid/uidmeta","path":"api_http/uid/uidmeta","type":"HTTP API"},{"name":"/api/version","path":"api_http/version","type":"HTTP API"},{"name":"/s","path":"api_http/s","type":"HTTP API"},{"name":"Additional Resources","path":"resources","type":"Miscellaneous"},{"name":"Aggregators","path":"user_guide/query/aggregators","type":"User Guide: Querying or Reading Data"},{"name":"Alerting with Nagios","path":"user_guide/utilities/nagios","type":"User Guide: Utilities"},{"name":"Bigtable","path":"user_guide/backends/bigtable","type":"User Guide: Storage"},{"name":"Cassandra","path":"user_guide/backends/cassandra","type":"User Guide: Storage"},{"name":"clean_cache.sh","path":"user_guide/utilities/clean_cache","type":"User Guide: Utilities"},{"name":"CLI Tools","path":"user_guide/cli/index","type":"User Guide: CLI Tools"},{"name":"Configuration","path":"user_guide/configuration","type":"User Guide"},{"name":"Dates and Times","path":"user_guide/query/dates","type":"User Guide: Querying or Reading Data"},{"name":"Definitions","path":"user_guide/definitions","type":"User Guide"},{"name":"Deprecated HTTP API","path":"api_http/deprecated","type":"HTTP API"},{"name":"Development","path":"development/index","type":"Development"},{"name":"diediedie","path":"api_telnet/diediedie","type":"Telnet Style API"},{"name":"dropcaches","path":"api_telnet/dropcaches","type":"Telnet Style API"},{"name":"Filters","path":"user_guide/query/filters","type":"User Guide: Querying or Reading Data"},{"name":"fsck","path":"user_guide/cli/fsck","type":"User Guide: CLI Tools"},{"name":"General Development","path":"development/development","type":"Development"},{"name":"GUI","path":"user_guide/guis/index","type":"User Guide: GUI"},{"name":"HBase Schema","path":"user_guide/backends/hbase","type":"User Guide: Storage"},{"name":"help","path":"api_telnet/help","type":"Telnet Style API"},{"name":"HTTP API","path":"api_http/index","type":"HTTP API"},{"name":"HTTP API","path":"development/http_api","type":"Development"},{"name":"HTTP Serializers","path":"api_http/serializers/index","type":"HTTP API"},{"name":"import","path":"user_guide/cli/import","type":"User Guide: CLI Tools"},{"name":"Installation","path":"installation","type":"Miscellaneous"},{"name":"JSON Serializer","path":"api_http/serializers/json","type":"HTTP API"},{"name":"Load Balancing with Varnish","path":"user_guide/utilities/varnish","type":"User Guide: Utilities"},{"name":"Logging","path":"user_guide/logging","type":"User Guide"},{"name":"Metadata","path":"user_guide/metadata","type":"User Guide"},{"name":"mkmetric","path":"user_guide/cli/mkmetric","type":"User Guide: CLI Tools"},{"name":"Plugins","path":"development/plugins","type":"Development"},{"name":"Plugins","path":"user_guide/plugins","type":"User Guide"},{"name":"put","path":"api_telnet/put","type":"Telnet Style API"},{"name":"query","path":"user_guide/cli/query","type":"User Guide: CLI Tools"},{"name":"Query Details and Stats","path":"user_guide/query/stats","type":"User Guide: Querying or Reading Data"},{"name":"Query Examples","path":"user_guide/query/examples","type":"User Guide: Querying or Reading Data"},{"name":"Querying or Reading Data","path":"user_guide/query/index","type":"User Guide: Querying or Reading Data"},{"name":"Quick Start","path":"user_guide/quickstart","type":"Miscellaneous"},{"name":"rollup","path":"api_telnet/rollup","type":"Telnet Style API"},{"name":"Rollup And Pre-Aggregates","path":"user_guide/rollups","type":"User Guide"},{"name":"scan","path":"user_guide/cli/scan","type":"User Guide: CLI Tools"},{"name":"search","path":"user_guide/cli/search","type":"User Guide: CLI Tools"},{"name":"stats","path":"api_telnet/stats","type":"Telnet Style API"},{"name":"Stats","path":"user_guide/stats","type":"User Guide"},{"name":"Storage","path":"user_guide/backends/index","type":"User Guide: Storage"},{"name":"TCollector","path":"user_guide/utilities/tcollector","type":"User Guide: Utilities"},{"name":"Telnet Style API","path":"api_telnet/index","type":"Telnet Style API"},{"name":"Trees","path":"user_guide/trees","type":"User Guide"},{"name":"Troubleshooting","path":"user_guide/troubleshooting","type":"User Guide"},{"name":"tsd","path":"user_guide/cli/tsd","type":"User Guide: CLI Tools"},{"name":"tsddrain.py","path":"user_guide/utilities/tsddrain","type":"User Guide: Utilities"},{"name":"uid","path":"user_guide/cli/uid","type":"User Guide: CLI Tools"},{"name":"UIDs and TSUIDs","path":"user_guide/uids","type":"User Guide"},{"name":"Understanding Metrics and Time Series","path":"user_guide/query/timeseries","type":"User Guide: Querying or Reading Data"},{"name":"User Guide","path":"user_guide/index","type":"User Guide"},{"name":"Utilities","path":"user_guide/utilities/index","type":"User Guide: Utilities"},{"name":"version","path":"api_telnet/version","type":"Telnet Style API"},{"name":"What's New","path":"new","type":"Miscellaneous"},{"name":"Writing Data","path":"user_guide/writing/index","type":"User Guide: Writing Data"}],"types":[{"name":"Development","count":4,"slug":"development"},{"name":"HTTP API","count":38,"slug":"http-api"},{"name":"Miscellaneous","count":4,"slug":"miscellaneous"},{"name":"Telnet Style API","count":8,"slug":"telnet-style-api"},{"name":"User Guide","count":11,"slug":"user-guide"},{"name":"User Guide: CLI Tools","count":9,"slug":"user-guide-cli-tools"},{"name":"User Guide: GUI","count":1,"slug":"user-guide-gui"},{"name":"User Guide: Querying or Reading Data","count":7,"slug":"user-guide-querying-or-reading-data"},{"name":"User Guide: Storage","count":4,"slug":"user-guide-storage"},{"name":"User Guide: Utilities","count":6,"slug":"user-guide-utilities"},{"name":"User Guide: Writing Data","count":1,"slug":"user-guide-writing-data"}]}