{"entries":[{"name":"a","path":"element/a","type":"Elements"},{"name":"accent-height","path":"attribute/accent-height","type":"Attributes"},{"name":"accumulate","path":"attribute/accumulate","type":"Attributes"},{"name":"additive","path":"attribute/additive","type":"Attributes"},{"name":"alignment-baseline","path":"attribute/alignment-baseline","type":"Attributes"},{"name":"altglyph","path":"element/altglyph","type":"Elements"},{"name":"altglyphdef","path":"element/altglyphdef","type":"Elements"},{"name":"altglyphitem","path":"element/altglyphitem","type":"Elements"},{"name":"angle","path":"content_type#Angle","type":"Content types"},{"name":"animate","path":"element/animate","type":"Elements"},{"name":"animatecolor","path":"element/animatecolor","type":"Elements"},{"name":"animatemotion","path":"element/animatemotion","type":"Elements"},{"name":"animatetransform","path":"element/animatetransform","type":"Elements"},{"name":"anything","path":"content_type#Anything","type":"Content types"},{"name":"Applying SVG effects to HTML content","path":"applying_svg_effects_to_html_content","type":"Miscellaneous"},{"name":"ascent","path":"attribute/ascent","type":"Attributes"},{"name":"attributename","path":"attribute/attributename","type":"Attributes"},{"name":"Attributes","path":"attribute","type":"Attributes"},{"name":"attributetype","path":"attribute/attributetype","type":"Attributes"},{"name":"azimuth","path":"attribute/azimuth","type":"Attributes"},{"name":"basefrequency","path":"attribute/basefrequency","type":"Attributes"},{"name":"baseline-shift","path":"attribute/baseline-shift","type":"Attributes"},{"name":"baseprofile","path":"attribute/baseprofile","type":"Attributes"},{"name":"Basic Shapes","path":"tutorial/basic_shapes","type":"Tutorial"},{"name":"Basic Transformations","path":"tutorial/basic_transformations","type":"Tutorial"},{"name":"begin","path":"attribute/begin","type":"Attributes"},{"name":"bias","path":"attribute/bias","type":"Attributes"},{"name":"calcmode","path":"attribute/calcmode","type":"Attributes"},{"name":"circle","path":"element/circle","type":"Elements"},{"name":"class","path":"attribute/class","type":"Attributes"},{"name":"clip","path":"attribute/clip","type":"Attributes"},{"name":"clip-path","path":"attribute/clip-path","type":"Attributes"},{"name":"clip-rule","path":"attribute/clip-rule","type":"Attributes"},{"name":"clippath","path":"element/clippath","type":"Elements"},{"name":"clippathunits","path":"attribute/clippathunits","type":"Attributes"},{"name":"Clipping and masking","path":"tutorial/clipping_and_masking","type":"Tutorial"},{"name":"clock-value","path":"content_type#Clock-value","type":"Content types"},{"name":"color","path":"content_type#Color","type":"Content types"},{"name":"color","path":"attribute/color","type":"Attributes"},{"name":"color-interpolation","path":"attribute/color-interpolation","type":"Attributes"},{"name":"color-interpolation-filters","path":"attribute/color-interpolation-filters","type":"Attributes"},{"name":"color-profile","path":"element/color-profile","type":"Elements"},{"name":"color-profile","path":"attribute/color-profile","type":"Attributes"},{"name":"color-rendering","path":"attribute/color-rendering","type":"Attributes"},{"name":"Content types","path":"content_type","type":"Content types"},{"name":"contentscripttype","path":"attribute/contentscripttype","type":"Attributes"},{"name":"contentstyletype","path":"attribute/contentstyletype","type":"Attributes"},{"name":"coordinate","path":"content_type#Coordinate","type":"Content types"},{"name":"cursor","path":"attribute/cursor","type":"Attributes"},{"name":"cursor","path":"element/cursor","type":"Elements"},{"name":"cx","path":"attribute/cx","type":"Attributes"},{"name":"cy","path":"attribute/cy","type":"Attributes"},{"name":"d","path":"attribute/d","type":"Attributes"},{"name":"defs","path":"element/defs","type":"Elements"},{"name":"desc","path":"element/desc","type":"Elements"},{"name":"diffuseconstant","path":"attribute/diffuseconstant","type":"Attributes"},{"name":"direction","path":"attribute/direction","type":"Attributes"},{"name":"discard","path":"element/discard","type":"Elements"},{"name":"display","path":"attribute/display","type":"Attributes"},{"name":"divisor","path":"attribute/divisor","type":"Attributes"},{"name":"dominant-baseline","path":"attribute/dominant-baseline","type":"Attributes"},{"name":"dur","path":"attribute/dur","type":"Attributes"},{"name":"dx","path":"attribute/dx","type":"Attributes"},{"name":"dy","path":"attribute/dy","type":"Attributes"},{"name":"edgemode","path":"attribute/edgemode","type":"Attributes"},{"name":"Elements","path":"element","type":"Elements"},{"name":"elevation","path":"attribute/elevation","type":"Attributes"},{"name":"ellipse","path":"element/ellipse","type":"Elements"},{"name":"end","path":"attribute/end","type":"Attributes"},{"name":"externalresourcesrequired","path":"attribute/externalresourcesrequired","type":"Attributes"},{"name":"feblend","path":"element/feblend","type":"Elements"},{"name":"fecolormatrix","path":"element/fecolormatrix","type":"Elements"},{"name":"fecomponenttransfer","path":"element/fecomponenttransfer","type":"Elements"},{"name":"fecomposite","path":"element/fecomposite","type":"Elements"},{"name":"feconvolvematrix","path":"element/feconvolvematrix","type":"Elements"},{"name":"fediffuselighting","path":"element/fediffuselighting","type":"Elements"},{"name":"fedisplacementmap","path":"element/fedisplacementmap","type":"Elements"},{"name":"fedistantlight","path":"element/fedistantlight","type":"Elements"},{"name":"fedropshadow","path":"element/fedropshadow","type":"Elements"},{"name":"feflood","path":"element/feflood","type":"Elements"},{"name":"fefunca","path":"element/fefunca","type":"Elements"},{"name":"fefuncb","path":"element/fefuncb","type":"Elements"},{"name":"fefuncg","path":"element/fefuncg","type":"Elements"},{"name":"fefuncr","path":"element/fefuncr","type":"Elements"},{"name":"fegaussianblur","path":"element/fegaussianblur","type":"Elements"},{"name":"feimage","path":"element/feimage","type":"Elements"},{"name":"femerge","path":"element/femerge","type":"Elements"},{"name":"femergenode","path":"element/femergenode","type":"Elements"},{"name":"femorphology","path":"element/femorphology","type":"Elements"},{"name":"feoffset","path":"element/feoffset","type":"Elements"},{"name":"fepointlight","path":"element/fepointlight","type":"Elements"},{"name":"fespecularlighting","path":"element/fespecularlighting","type":"Elements"},{"name":"fespotlight","path":"element/fespotlight","type":"Elements"},{"name":"fetile","path":"element/fetile","type":"Elements"},{"name":"feturbulence","path":"element/feturbulence","type":"Elements"},{"name":"fill","path":"attribute/fill","type":"Attributes"},{"name":"fill-opacity","path":"attribute/fill-opacity","type":"Attributes"},{"name":"fill-rule","path":"attribute/fill-rule","type":"Attributes"},{"name":"Fills and Strokes","path":"tutorial/fills_and_strokes","type":"Tutorial"},{"name":"filter","path":"attribute/filter","type":"Attributes"},{"name":"filter","path":"element/filter","type":"Elements"},{"name":"Filter effects","path":"tutorial/filter_effects","type":"Tutorial"},{"name":"filterres","path":"attribute/filterres","type":"Attributes"},{"name":"filterunits","path":"attribute/filterunits","type":"Attributes"},{"name":"flood-color","path":"attribute/flood-color","type":"Attributes"},{"name":"flood-opacity","path":"attribute/flood-opacity","type":"Attributes"},{"name":"font","path":"element/font","type":"Elements"},{"name":"font-face","path":"element/font-face","type":"Elements"},{"name":"font-face-format","path":"element/font-face-format","type":"Elements"},{"name":"font-face-name","path":"element/font-face-name","type":"Elements"},{"name":"font-face-src","path":"element/font-face-src","type":"Elements"},{"name":"font-face-uri","path":"element/font-face-uri","type":"Elements"},{"name":"font-family","path":"attribute/font-family","type":"Attributes"},{"name":"font-size","path":"attribute/font-size","type":"Attributes"},{"name":"font-size-adjust","path":"attribute/font-size-adjust","type":"Attributes"},{"name":"font-stretch","path":"attribute/font-stretch","type":"Attributes"},{"name":"font-style","path":"attribute/font-style","type":"Attributes"},{"name":"font-variant","path":"attribute/font-variant","type":"Attributes"},{"name":"font-weight","path":"attribute/font-weight","type":"Attributes"},{"name":"foreignobject","path":"element/foreignobject","type":"Elements"},{"name":"fr","path":"attribute/fr","type":"Attributes"},{"name":"frequency","path":"content_type#Frequency","type":"Content types"},{"name":"from","path":"attribute/from","type":"Attributes"},{"name":"FuncIRI","path":"content_type#FuncIRI","type":"Content types"},{"name":"fx","path":"attribute/fx","type":"Attributes"},{"name":"fy","path":"attribute/fy","type":"Attributes"},{"name":"g","path":"element/g","type":"Elements"},{"name":"Getting Started","path":"tutorial/getting_started","type":"Tutorial"},{"name":"glyph","path":"element/glyph","type":"Elements"},{"name":"glyphref","path":"element/glyphref","type":"Elements"},{"name":"Gradients","path":"tutorial/gradients","type":"Tutorial"},{"name":"gradienttransform","path":"attribute/gradienttransform","type":"Attributes"},{"name":"gradientunits","path":"attribute/gradientunits","type":"Attributes"},{"name":"hatch","path":"element/hatch","type":"Elements"},{"name":"hatchpath","path":"element/hatchpath","type":"Elements"},{"name":"height","path":"attribute/height","type":"Attributes"},{"name":"hkern","path":"element/hkern","type":"Elements"},{"name":"href","path":"attribute/href","type":"Attributes"},{"name":"icccolor","path":"content_type#ICCColor","type":"Content types"},{"name":"image","path":"element/image","type":"Elements"},{"name":"image-rendering","path":"attribute/image-rendering","type":"Attributes"},{"name":"in","path":"attribute/in","type":"Attributes"},{"name":"in2","path":"attribute/in2","type":"Attributes"},{"name":"integer","path":"content_type#Integer","type":"Content types"},{"name":"Introduction","path":"tutorial/introduction","type":"Tutorial"},{"name":"IRI","path":"content_type#IRI","type":"Content types"},{"name":"k1","path":"attribute/k1","type":"Attributes"},{"name":"k2","path":"attribute/k2","type":"Attributes"},{"name":"k3","path":"attribute/k3","type":"Attributes"},{"name":"k4","path":"attribute/k4","type":"Attributes"},{"name":"kernelmatrix","path":"attribute/kernelmatrix","type":"Attributes"},{"name":"kernelunitlength","path":"attribute/kernelunitlength","type":"Attributes"},{"name":"kerning","path":"attribute/kerning","type":"Attributes"},{"name":"keysplines","path":"attribute/keysplines","type":"Attributes"},{"name":"keytimes","path":"attribute/keytimes","type":"Attributes"},{"name":"length","path":"content_type#Length","type":"Content types"},{"name":"lengthadjust","path":"attribute/lengthadjust","type":"Attributes"},{"name":"letter-spacing","path":"attribute/letter-spacing","type":"Attributes"},{"name":"lighting-color","path":"attribute/lighting-color","type":"Attributes"},{"name":"limitingconeangle","path":"attribute/limitingconeangle","type":"Attributes"},{"name":"line","path":"element/line","type":"Elements"},{"name":"lineargradient","path":"element/lineargradient","type":"Elements"},{"name":"list-of-Ts","path":"content_type#List-of-Ts","type":"Content types"},{"name":"local","path":"attribute/local","type":"Attributes"},{"name":"marker","path":"element/marker","type":"Elements"},{"name":"marker-end","path":"attribute/marker-end","type":"Attributes"},{"name":"marker-mid","path":"attribute/marker-mid","type":"Attributes"},{"name":"marker-start","path":"attribute/marker-start","type":"Attributes"},{"name":"markerheight","path":"attribute/markerheight","type":"Attributes"},{"name":"markerunits","path":"attribute/markerunits","type":"Attributes"},{"name":"markerwidth","path":"attribute/markerwidth","type":"Attributes"},{"name":"mask","path":"attribute/mask","type":"Attributes"},{"name":"mask","path":"element/mask","type":"Elements"},{"name":"maskcontentunits","path":"attribute/maskcontentunits","type":"Attributes"},{"name":"maskunits","path":"attribute/maskunits","type":"Attributes"},{"name":"max","path":"attribute/max","type":"Attributes"},{"name":"metadata","path":"element/metadata","type":"Elements"},{"name":"min","path":"attribute/min","type":"Attributes"},{"name":"missing-glyph","path":"element/missing-glyph","type":"Elements"},{"name":"mode","path":"attribute/mode","type":"Attributes"},{"name":"mpath","path":"element/mpath","type":"Elements"},{"name":"name","path":"content_type#Name","type":"Content types"},{"name":"number","path":"content_type#Number","type":"Content types"},{"name":"number-optional-number","path":"content_type#Number-optional-number","type":"Content types"},{"name":"numoctaves","path":"attribute/numoctaves","type":"Attributes"},{"name":"opacity","path":"attribute/opacity","type":"Attributes"},{"name":"opacity-value","path":"content_type#Opacity_value","type":"Content types"},{"name":"operator","path":"attribute/operator","type":"Attributes"},{"name":"order","path":"attribute/order","type":"Attributes"},{"name":"Other content in SVG","path":"tutorial/other_content_in_svg","type":"Tutorial"},{"name":"overflow","path":"attribute/overflow","type":"Attributes"},{"name":"overline-position","path":"attribute/overline-position","type":"Attributes"},{"name":"overline-thickness","path":"attribute/overline-thickness","type":"Attributes"},{"name":"paint","path":"content_type#Paint","type":"Content types"},{"name":"paint-order","path":"attribute/paint-order","type":"Attributes"},{"name":"path","path":"element/path","type":"Elements"},{"name":"pathlength","path":"attribute/pathlength","type":"Attributes"},{"name":"Paths","path":"tutorial/paths","type":"Tutorial"},{"name":"pattern","path":"element/pattern","type":"Elements"},{"name":"patterncontentunits","path":"attribute/patterncontentunits","type":"Attributes"},{"name":"Patterns","path":"tutorial/patterns","type":"Tutorial"},{"name":"patterntransform","path":"attribute/patterntransform","type":"Attributes"},{"name":"patternunits","path":"attribute/patternunits","type":"Attributes"},{"name":"percentage","path":"content_type#Percentage","type":"Content types"},{"name":"pointer-events","path":"attribute/pointer-events","type":"Attributes"},{"name":"points","path":"attribute/points","type":"Attributes"},{"name":"pointsatx","path":"attribute/pointsatx","type":"Attributes"},{"name":"pointsaty","path":"attribute/pointsaty","type":"Attributes"},{"name":"pointsatz","path":"attribute/pointsatz","type":"Attributes"},{"name":"polygon","path":"element/polygon","type":"Elements"},{"name":"polyline","path":"element/polyline","type":"Elements"},{"name":"Positions","path":"tutorial/positions","type":"Tutorial"},{"name":"preservealpha","path":"attribute/preservealpha","type":"Attributes"},{"name":"preserveaspectratio","path":"attribute/preserveaspectratio","type":"Attributes"},{"name":"primitiveunits","path":"attribute/primitiveunits","type":"Attributes"},{"name":"r","path":"attribute/r","type":"Attributes"},{"name":"radialgradient","path":"element/radialgradient","type":"Elements"},{"name":"radius","path":"attribute/radius","type":"Attributes"},{"name":"rect","path":"element/rect","type":"Elements"},{"name":"refx","path":"attribute/refx","type":"Attributes"},{"name":"repeatcount","path":"attribute/repeatcount","type":"Attributes"},{"name":"repeatdur","path":"attribute/repeatdur","type":"Attributes"},{"name":"requiredfeatures","path":"attribute/requiredfeatures","type":"Attributes"},{"name":"restart","path":"attribute/restart","type":"Attributes"},{"name":"result","path":"attribute/result","type":"Attributes"},{"name":"rx","path":"attribute/rx","type":"Attributes"},{"name":"ry","path":"attribute/ry","type":"Attributes"},{"name":"scale","path":"attribute/scale","type":"Attributes"},{"name":"script","path":"element/script","type":"Elements"},{"name":"seed","path":"attribute/seed","type":"Attributes"},{"name":"set","path":"element/set","type":"Elements"},{"name":"shape-rendering","path":"attribute/shape-rendering","type":"Attributes"},{"name":"solidcolor","path":"element/solidcolor","type":"Elements"},{"name":"specularconstant","path":"attribute/specularconstant","type":"Attributes"},{"name":"specularexponent","path":"attribute/specularexponent","type":"Attributes"},{"name":"stddeviation","path":"attribute/stddeviation","type":"Attributes"},{"name":"stitchtiles","path":"attribute/stitchtiles","type":"Attributes"},{"name":"stop","path":"element/stop","type":"Elements"},{"name":"stop-color","path":"attribute/stop-color","type":"Attributes"},{"name":"stop-opacity","path":"attribute/stop-opacity","type":"Attributes"},{"name":"strikethrough-position","path":"attribute/strikethrough-position","type":"Attributes"},{"name":"strikethrough-thickness","path":"attribute/strikethrough-thickness","type":"Attributes"},{"name":"stroke","path":"attribute/stroke","type":"Attributes"},{"name":"stroke-dasharray","path":"attribute/stroke-dasharray","type":"Attributes"},{"name":"stroke-dashoffset","path":"attribute/stroke-dashoffset","type":"Attributes"},{"name":"stroke-linecap","path":"attribute/stroke-linecap","type":"Attributes"},{"name":"stroke-linejoin","path":"attribute/stroke-linejoin","type":"Attributes"},{"name":"stroke-miterlimit","path":"attribute/stroke-miterlimit","type":"Attributes"},{"name":"stroke-opacity","path":"attribute/stroke-opacity","type":"Attributes"},{"name":"stroke-width","path":"attribute/stroke-width","type":"Attributes"},{"name":"style","path":"element/style","type":"Elements"},{"name":"style","path":"attribute/style","type":"Attributes"},{"name":"surfacescale","path":"attribute/surfacescale","type":"Attributes"},{"name":"svg","path":"element/svg","type":"Elements"},{"name":"SVG and CSS","path":"tutorial/svg_and_css","type":"Tutorial"},{"name":"SVG animation with SMIL","path":"svg_animation_with_smil","type":"Miscellaneous"},{"name":"SVG as an Image","path":"svg_as_an_image","type":"Miscellaneous"},{"name":"SVG fonts","path":"tutorial/svg_fonts","type":"Tutorial"},{"name":"SVG Image Tag","path":"tutorial/svg_image_tag","type":"Tutorial"},{"name":"switch","path":"element/switch","type":"Elements"},{"name":"symbol","path":"element/symbol","type":"Elements"},{"name":"tabindex","path":"attribute/tabindex","type":"Attributes"},{"name":"targetx","path":"attribute/targetx","type":"Attributes"},{"name":"targety","path":"attribute/targety","type":"Attributes"},{"name":"text","path":"element/text","type":"Elements"},{"name":"text-anchor","path":"attribute/text-anchor","type":"Attributes"},{"name":"text-decoration","path":"attribute/text-decoration","type":"Attributes"},{"name":"text-rendering","path":"attribute/text-rendering","type":"Attributes"},{"name":"textlength","path":"attribute/textlength","type":"Attributes"},{"name":"textpath","path":"element/textpath","type":"Elements"},{"name":"Texts","path":"tutorial/texts","type":"Tutorial"},{"name":"time","path":"content_type#Time","type":"Content types"},{"name":"title","path":"element/title","type":"Elements"},{"name":"to","path":"attribute/to","type":"Attributes"},{"name":"Tools for SVG","path":"tutorial/tools_for_svg","type":"Tutorial"},{"name":"transform","path":"attribute/transform","type":"Attributes"},{"name":"transform-list","path":"content_type#Transform-list","type":"Content types"},{"name":"tref","path":"element/tref","type":"Elements"},{"name":"tspan","path":"element/tspan","type":"Elements"},{"name":"Tutorial","path":"tutorial","type":"Tutorial"},{"name":"type","path":"attribute/type","type":"Attributes"},{"name":"underline-position","path":"attribute/underline-position","type":"Attributes"},{"name":"underline-thickness","path":"attribute/underline-thickness","type":"Attributes"},{"name":"URL","path":"content_type#URL","type":"Content types"},{"name":"use","path":"element/use","type":"Elements"},{"name":"values","path":"attribute/values","type":"Attributes"},{"name":"vector-effect","path":"attribute/vector-effect","type":"Attributes"},{"name":"version","path":"attribute/version","type":"Attributes"},{"name":"view","path":"element/view","type":"Elements"},{"name":"viewbox","path":"attribute/viewbox","type":"Attributes"},{"name":"visibility","path":"attribute/visibility","type":"Attributes"},{"name":"vkern","path":"element/vkern","type":"Elements"},{"name":"width","path":"attribute/width","type":"Attributes"},{"name":"word-spacing","path":"attribute/word-spacing","type":"Attributes"},{"name":"writing-mode","path":"attribute/writing-mode","type":"Attributes"},{"name":"x","path":"attribute/x","type":"Attributes"},{"name":"x1","path":"attribute/x1","type":"Attributes"},{"name":"x2","path":"attribute/x2","type":"Attributes"},{"name":"xchannelselector","path":"attribute/xchannelselector","type":"Attributes"},{"name":"xlink:href","path":"attribute/xlink:href","type":"Attributes"},{"name":"xlink:show","path":"attribute/xlink:show","type":"Attributes"},{"name":"xlink:title","path":"attribute/xlink:title","type":"Attributes"},{"name":"xml:lang","path":"attribute/xml:lang","type":"Attributes"},{"name":"xml:space","path":"attribute/xml:space","type":"Attributes"},{"name":"y","path":"attribute/y","type":"Attributes"},{"name":"y1","path":"attribute/y1","type":"Attributes"},{"name":"y2","path":"attribute/y2","type":"Attributes"},{"name":"ychannelselector","path":"attribute/ychannelselector","type":"Attributes"},{"name":"z","path":"attribute/z","type":"Attributes"}],"types":[{"name":"Attributes","count":180,"slug":"attributes"},{"name":"Content types","count":22,"slug":"content-types"},{"name":"Elements","count":86,"slug":"elements"},{"name":"Miscellaneous","count":3,"slug":"miscellaneous"},{"name":"Tutorial","count":18,"slug":"tutorial"}]}